WCX-0.1.8.dist-info/DESCRIPTION.rst
WCX-0.1.8.dist-info/METADATA
WCX-0.1.8.dist-info/RECORD
WCX-0.1.8.dist-info/WHEEL
WCX-0.1.8.dist-info/metadata.json
WCX-0.1.8.dist-info/top_level.txt
wcx/__init__.py
