Metadata-Version: 2.0
Name: WCX
Version: 0.1.8
Summary: The easiest way to integrate WCX Api Functions in your applications. Sign up at WCX.com for your API key.
Home-page: http://www.osiztechnologies.com/
Author: OsizTech
Author-email: veerasarma@osiztechnologies.com
License: ISC
Keywords: WCX wcx_wallet bitcoin_api wcx wallet wcx_wallet_api
Platform: UNKNOWN
Requires-Dist: base58
Requires-Dist: ecdsa
Requires-Dist: pycrypto
Requires-Dist: requests
Requires-Dist: six
